datamodel/__init__.py
datamodel/data_source.py
environment/__init__.py
environment/environment.py
report/__init__.py
report/report.py
reportmodel/__init__.py
reportmodel/report_generator.py
reportmodel/template.py
templatte-0.2.dist-info/LICENSE
templatte-0.2.dist-info/METADATA
templatte-0.2.dist-info/WHEEL
templatte-0.2.dist-info/top_level.txt
templatte-0.2.dist-info/RECORD
