Metadata-Version: 2.1
Name: templatte
Version: 0.2
Summary: Easy to use SDK for beautiful PDF reports
Home-page: https://github.com/cinegemadar/templatter
Author: David Balogh
Author-email: mail@davidbalogh.me
License: MIT
License-File: LICENSE
Requires-Dist: Jinja2
Requires-Dist: pandas
Requires-Dist: pdfkit
Requires-Dist: openpyxl
